{
  "$schema": "https://schema.management.azure.com/schemas/2019-04-01/deploymentTemplate.json#",
  "contentVersion": "1.0.0.0",
  "parameters": {
    "ApimServiceName": {
      "type": "string"
    }
  },
  "resources": [
    {
      "properties": {
        "tags": [],
        "secret": false,
        "displayName": "TimeNow",
        "value": "@(DateTime.Now.ToString())"
      },
      "name": "[concat(parameters('ApimServiceName'), '/TimeNow')]",
      "type": "Microsoft.ApiManagement/service/namedValues",
      "apiVersion": "2021-01-01-preview"
    }
  ]
}